{
  "latest": "0.2.0",
  "buildCode": 3403748,
  "publishedAt": "2026-06-21",
  "notes": "### Nouveau jeu : Five Crowns (Les Cinq Rois)\n- Game type 👑 ajouté, règles imposées (11 manches, plus petit gagne, solo strict).\n- Variante Express (6 manches au lieu de 11) en checkbox dans le setup.\n- Règles officielles Gigamic transcrites en Markdown intégral + 2 pages du PDF officiel converties en PNG haute-résolution.\n\n### Page Règles complètes\n- Nouvelle page `/rules/{slug}` accessible depuis :\n  - les cartes de l'onglet **Jeux** (bouton « 📖 Règles »)\n  - le header de chaque partie en cours (Belote, Yams, Five Crowns)\n- Rendu Markdown (titres, listes, tableaux, blockquotes) + galerie des pages PDF officielles avec zoom plein écran.\n- Bouton retour contextuel : ramène à la partie si on est venu d'une session, à la liste des jeux sinon.\n\n### Compteur générique : mode équipe\n- Toggle « Chacun pour soi / Par équipes » dans le setup.\n- 2 à N équipes (illimité), composition par drag-tap : sélectionner une équipe puis taper les joueurs du pool pour les y ajouter.\n- Choix du mode de saisie : **par équipe** (1 input, comme Belote) ou **par joueur** (le total équipe = somme).\n- Affichage en session adapté : lignes par équipe avec membres listés (mode PerTeam) ou groupes de joueurs sous un header d'équipe (PerPlayer).\n- Couleur et nom d'équipe éditables (cycle dans une palette).\n\n### Belote : saisie simplifiée\n- Suppression du picker « 10 de der » : le 10 est toujours inclus dans les 162 points, plus de question.\n- Belote passe de 3 à 2 modes (Aucune / Belote +20).\n- Icônes ⏳ litige et ✨ bonus à gauche du score (les chiffres restent alignés à droite proprement).\n\n### Système de mises à jour intégré (Windows + Android)\n- Page « À propos » avec version installée, dernière dispo, changelog historique embarqué.\n- Vérification automatique au démarrage (debounce 6h) + banner discret quand une nouvelle version sort.\n- Android : téléchargement de l'APK signé + ouverture de l'écran d'installation système.\n- Windows : installeur Inno Setup (`ScoreCounter-setup-vX.Y.Z.exe`) + auto-update silencieuse via `/VERYSILENT /CLOSEAPPLICATIONS /RESTARTAPPLICATIONS`. Vérification SHA256 avant exécution.\n- Installer.iss vérifie .NET 10 Desktop Runtime + Windows App SDK Runtime et télécharge depuis aka.ms si manquant.\n- Keystore Android stable (`Secrets/scorecounter.keystore`) pour signer toutes les Release.\n- Repo public **kurokirito/score-counter-releases** pour binaires + manifeste `update.json`.\n\n### Refonte du design (audit P0 + P1)\n- Suppression d'un `.btn-primary` dupliqué qui écrasait le bouton principal partout dans l'app.\n- Tokens `--gold-ink` / `--cream` factorisés (9 valeurs hex en dur remplacées).\n- Light theme : overrides `.status.err/.ok/.litige` (étaient illisibles en sépia).\n- Modifiers de taille `.btn-lg` / `.btn-sm` / `.btn-block` introduits.\n- `.history-row` : `<button>` imbriqué dans `<button>` corrigé en `<div role=\"button\">` + handler clavier.\n- `.history-action` (Reprendre / Refaire / 🗑) refondu : Reprendre en gold plein, Refaire en transparent secondaire, 🗑 en icon-only discret. Layout horizontal même en mobile.\n- Topbar mobile réduite à 32px transparent (l'info était déjà dans la nav du bas).\n- Focus-visible corrigé sur chips/tiles.\n- `.score-pending` défini (border dashed + pulse).\n- Tables : `position: sticky` sur thead + 1ère colonne. Densité Belote alignée sur Yams (8px).\n\n### Belote : polish UX\n- Suppression des 2 gros encarts de totaux : totaux affichés directement dans le thead sticky de la table de donnes.\n- Composition d'équipes : bandeau discret avec membres au-dessus du tableau.\n- Ligne `.editing` (gold + barre or à gauche) sur la donne en cours d'édition.\n- Boutons « + Nouvelle donne » et « Terminer la partie » intégrés dans le `<tfoot>` sticky-bottom du tableau (plus de footer fixe sous le tableau).\n- Une seule scrollbar verticale (suppression du conflit de scroll page vs wrap).\n\n### À venir\n- Tarot.\n- Mode équipe : adapter aussi le tableau récap par manche (vue 📊).",
  "platforms": {
    "android": {
      "url": "https://github.com/kurokirito/score-counter-releases/releases/download/v0.2.0/ScoreCounter-android-v0.2.0.apk",
      "sha256": "37532ad469d95c2ac5be48b2aeafced5f1b8aaf412a36bddc180f1d8691cc3a2",
      "size": 49039379
    },
    "windows": {
      "url": "https://github.com/kurokirito/score-counter-releases/releases/download/v0.2.0/ScoreCounter-setup-v0.2.0.exe",
      "sha256": "baa2e02cbf1eddb985f9036480a31cf22189874b16dab6e09d94e4c1b62aee4f",
      "size": 58087849,
      "type": "inno-setup"
    }
  }
}