{
  "latest": "0.2.2",
  "buildCode": 3403914,
  "publishedAt": "2026-06-21",
  "notes": "### Ajouts\n- **Banner de mise à jour visible aussi sur l'écran de login** — utile quand une\n  nouvelle version corrige justement le système d'authentification (cas v0.2.1\n  pour Google OAuth sur Android). Le bouton \"Mettre à jour\" navigue vers la page\n  À propos qui marche sans login.",
  "platforms": {
    "android": {
      "url": "https://github.com/kurokirito/score-counter-releases/releases/download/v0.2.2/ScoreCounter-android-v0.2.2.apk",
      "sha256": "543cebaadec67ab18af8135981abd4eb0450a8d547e9e683eecc8eea05825309",
      "size": 49047571
    },
    "windows": {
      "url": "https://github.com/kurokirito/score-counter-releases/releases/download/v0.2.2/ScoreCounter-setup-v0.2.2.exe",
      "sha256": "eb55da20f8c98593959c020fdcae42c0ce8dd22920f71fa585018eeb6a588460",
      "size": 58087510,
      "type": "inno-setup"
    }
  }
}